pyEvalData/__init__.py
pyEvalData/config.py
pyEvalData/evaluation.py
pyEvalData/helpers.py
pyEvalData/plotting.py
pyEvalData/pyEvalData_default.conf
pyEvalData/io/__init__.py
pyEvalData/io/palxfel.py
pyEvalData/io/sardana_nexus.py
pyEvalData/io/scan.py
pyEvalData/io/source.py
pyEvalData/io/spec.py
test/__init__.py
test/conftest.py
test/test_evaluation.py
test/test_scan.py
test/test_source.py
pyEvalData-1.6.0.dist-info/LICENSE
pyEvalData-1.6.0.dist-info/METADATA
pyEvalData-1.6.0.dist-info/WHEEL
pyEvalData-1.6.0.dist-info/top_level.txt
pyEvalData-1.6.0.dist-info/RECORD
