Metadata-Version: 2.1
Name: pyEvalData
Version: 1.6.0
Summary: Python module to evaluate experimental data
Home-page: https://github.com/dschick/pyEvalData
Author: Daniel Schick
Author-email: schick.daniel@gmail.com
License: MIT
Keywords: data evaluation analysis SPEC h5 NeXus
Platform: UNKNOWN
Requires-Python: >=3.5
Requires-Dist: numpy
Requires-Dist: matplotlib
Requires-Dist: lmfit
Requires-Dist: scipy
Requires-Dist: uncertainties
Requires-Dist: xrayutilities
Requires-Dist: h5py >=3.0
Requires-Dist: nexusformat
Provides-Extra: documentation
Requires-Dist: sphinx ; extra == 'documentation'
Requires-Dist: nbsphinx ; extra == 'documentation'
Requires-Dist: sphinxcontrib-napoleon ; extra == 'documentation'
Provides-Extra: testing
Requires-Dist: flake8 ; extra == 'testing'
Requires-Dist: pytest ; extra == 'testing'
